blaze_cicd/__init__.py
blaze_cicd/argocd.py
blaze_cicd/cli.py
blaze_cicd/commands.py
blaze_cicd/data.py
blaze_cicd/docker.py
blaze_cicd/github.py
blaze_cicd/kubectl.py
tests/__init__.py
tests/test_cli.py
tests/test_docker.py
tests/test_github.py
blaze_cicd-1.0.2.dist-info/LICENSE
blaze_cicd-1.0.2.dist-info/METADATA
blaze_cicd-1.0.2.dist-info/WHEEL
blaze_cicd-1.0.2.dist-info/entry_points.txt
blaze_cicd-1.0.2.dist-info/top_level.txt
blaze_cicd-1.0.2.dist-info/RECORD
