Metadata-Version: 2.2
Name: blaze-cicd
Version: 1.0.2
Summary: A CLI tool for managing CI/CD pipelines with Docker, GitHub, and ArgoCD.
Author: Ahmed Rakan
Author-email: ar.aldhafeeri11@gmail.com
Project-URL: Source, https://github.com/yourusername/blaze-cicd
Project-URL: Bug Reports, https://github.com/araldhafeeri/blaze-cicd/issues
Classifier: Development Status :: 3 - Alpha
Classifier: Intended Audience :: Developers
Classifier: License :: OSI Approved :: MIT License
Classifier: Programming Language :: Python :: 3
Classifier: Programming Language :: Python :: 3.8
Classifier: Programming Language :: Python :: 3.9
Classifier: Programming Language :: Python :: 3.10
Classifier: Operating System :: OS Independent
Requires-Python: >=3.8
License-File: LICENSE
Requires-Dist: requests>=2.31.0
Requires-Dist: PyYAML>=6.0.0
Dynamic: author
Dynamic: author-email
Dynamic: classifier
Dynamic: description
Dynamic: description-content-type
Dynamic: project-url
Dynamic: requires-dist
Dynamic: requires-python
Dynamic: summary
